pybfbc2stats/__init__.py
pybfbc2stats/asyncio_client.py
pybfbc2stats/asyncio_connection.py
pybfbc2stats/buffer.py
pybfbc2stats/client.py
pybfbc2stats/connection.py
pybfbc2stats/constants.py
pybfbc2stats/exceptions.py
pybfbc2stats/logger.py
pybfbc2stats/packet.py
pybfbc2stats/payload.py
pybfbc2stats/rome.py
pybfbc2stats-0.8.1.dist-info/LICENSE.md
pybfbc2stats-0.8.1.dist-info/METADATA
pybfbc2stats-0.8.1.dist-info/WHEEL
pybfbc2stats-0.8.1.dist-info/top_level.txt
pybfbc2stats-0.8.1.dist-info/RECORD
