Metadata-Version: 2.1
Name: pybfbc2stats
Version: 0.8.1
Summary: Python library for retrieving statistics of Battlefield: Bad Company 2 players
Home-page: https://github.com/cetteup/pybfbc2stats
Author: cetteup
Author-email: me@cetteup.com
License: MIT
Project-URL: Bug Tracker, https://github.com/cetteup/pybfbc2stats/issues
Classifier: Development Status :: 4 - Beta
Classifier: Intended Audience :: Developers
Classifier: License :: OSI Approved :: MIT License
Classifier: Operating System :: OS Independent
Classifier: Programming Language :: Python :: 3
Requires-Python: >=3.8
License-File: LICENSE.md
